bulketl/__init__.py
bulketl/bulketl.py
bulketl-0.0.1.dist-info/LICENSE
bulketl-0.0.1.dist-info/METADATA
bulketl-0.0.1.dist-info/WHEEL
bulketl-0.0.1.dist-info/top_level.txt
bulketl-0.0.1.dist-info/RECORD
